CONTRIBUTING.md
MANIFEST.in
README.rst
constraints.txt
requirements.txt
setup.py
docs/HISTORY.txt
docs/LICENSE.GPL
docs/LICENSE.txt
eea/__init__.py
eea.api.dataconnector.egg-info/PKG-INFO
eea.api.dataconnector.egg-info/SOURCES.txt
eea.api.dataconnector.egg-info/dependency_links.txt
eea.api.dataconnector.egg-info/entry_points.txt
eea.api.dataconnector.egg-info/namespace_packages.txt
eea.api.dataconnector.egg-info/not-zip-safe
eea.api.dataconnector.egg-info/requires.txt
eea.api.dataconnector.egg-info/top_level.txt
eea/api/__init__.py
eea/api/dataconnector/README.txt
eea/api/dataconnector/__init__.py
eea/api/dataconnector/adapter.py
eea/api/dataconnector/behavior.py
eea/api/dataconnector/behavior.zcml
eea/api/dataconnector/configure.zcml
eea/api/dataconnector/interfaces.py
eea/api/dataconnector/io_csv.py
eea/api/dataconnector/permissions.zcml
eea/api/dataconnector/profiles.zcml
eea/api/dataconnector/queryfilter.py
eea/api/dataconnector/queryparser.py
eea/api/dataconnector/setuphandlers.py
eea/api/dataconnector/utils.py
eea/api/dataconnector/version.txt
eea/api/dataconnector/api/__init__.py
eea/api/dataconnector/api/configure.zcml
eea/api/dataconnector/api/dataconnector.py
eea/api/dataconnector/browser/__init__.py
eea/api/dataconnector/browser/blocks.py
eea/api/dataconnector/browser/configure.zcml
eea/api/dataconnector/browser/dataprovider.py
eea/api/dataconnector/browser/flourish.py
eea/api/dataconnector/browser/pt/arcgis_map_view.pt
eea/api/dataconnector/browser/pt/data_connector_view.pt
eea/api/dataconnector/browser/pt/flourish_upload.pt
eea/api/dataconnector/browser/pt/provided_data.pt
eea/api/dataconnector/browser/pt/tableau_view.pt
eea/api/dataconnector/locales/__init__.py
eea/api/dataconnector/locales/eea.pot
eea/api/dataconnector/locales/plone-manual.pot
eea/api/dataconnector/locales/update.sh
eea/api/dataconnector/locales/bg/LC_MESSAGES/eea.po
eea/api/dataconnector/locales/bg/LC_MESSAGES/plone.po
eea/api/dataconnector/locales/cs/LC_MESSAGES/eea.po
eea/api/dataconnector/locales/cs/LC_MESSAGES/plone.po
eea/api/dataconnector/locales/da/LC_MESSAGES/eea.po
eea/api/dataconnector/locales/da/LC_MESSAGES/plone.po
eea/api/dataconnector/locales/de/LC_MESSAGES/eea.po
eea/api/dataconnector/locales/de/LC_MESSAGES/plone.po
eea/api/dataconnector/locales/el/LC_MESSAGES/eea.po
eea/api/dataconnector/locales/el/LC_MESSAGES/plone.po
